llq/__init__.py
llq/demo.py
llq/that.py
llq/util/__init__.py
llq/util/data/__init__.py
llq/util/data/fakeData.py
llq/util/data/slide_window.py
llq/util/devices/GPU.py
llq/util/devices/__init__.py
llq/util/network/__init__.py
llq/util/network/baiduTop.py
llq/util/network/wifi.py
prof_llq_tools-0.9.11.dist-info/METADATA
prof_llq_tools-0.9.11.dist-info/WHEEL
prof_llq_tools-0.9.11.dist-info/top_level.txt
prof_llq_tools-0.9.11.dist-info/RECORD
