Metadata-Version: 2.1
Name: prof-llq-tools
Version: 0.9.11
Summary: My Python Tools
Home-page: https://www.shnu.edu.cn
Author: Prof.Luqun Li
Author-email: liluqun@gmail.com
Project-URL: Bug Tracker, https://www.shnu.edu.cn
Classifier: Programming Language :: Python :: 3
Classifier: License :: OSI Approved :: MIT License
Classifier: Operating System :: OS Independent
Requires-Python: >=3.6
